rydiqule/__init__.py
rydiqule/__version__.py
rydiqule/arc_utils.py
rydiqule/atom_utils.py
rydiqule/cell.py
rydiqule/conftest.py
rydiqule/doppler_exact.py
rydiqule/doppler_utils.py
rydiqule/exceptions.py
rydiqule/experiments.py
rydiqule/rydiqule_utils.py
rydiqule/sensor.py
rydiqule/sensor_solution.py
rydiqule/sensor_utils.py
rydiqule/solvers.py
rydiqule/timesolvers.py
rydiqule/slicing/__init__.py
rydiqule/slicing/slicing.py
rydiqule/stack_solvers/__init__.py
rydiqule/stack_solvers/cyrk_solver.py
rydiqule/stack_solvers/scipy_solver.py
rydiqule-2.1.1.dist-info/licenses/LICENSE
rydiqule-2.1.1.dist-info/METADATA
rydiqule-2.1.1.dist-info/WHEEL
rydiqule-2.1.1.dist-info/top_level.txt
rydiqule-2.1.1.dist-info/RECORD
