Metadata-Version: 2.4
Name: rydiqule
Version: 2.1.1
Summary: Rydberg Sensor Interactive Quantum Physics Module
Author: ARL and NAWCWD
License: Apache
Keywords: rydberg,atomic-physics,quantum-optics,atomic-sensors,electrometry
Classifier: Development Status :: 5 - Production/Stable
Classifier: License :: OSI Approved :: Apache Software License
Classifier: Programming Language :: Python :: 3 :: Only
Requires-Python: >=3.8
License-File: LICENSE
Requires-Dist: arc-alkali-rydberg-calculator>=3.5.0
Requires-Dist: numpy
Requires-Dist: scipy>=0.19.1
Requires-Dist: leveldiagram>=0.3.1
Requires-Dist: networkx
Requires-Dist: psutil
Requires-Dist: typing-extensions
Provides-Extra: backends
Requires-Dist: numba; extra == "backends"
Requires-Dist: cyrk>=0.12.1; extra == "backends"
Provides-Extra: docs
Requires-Dist: Sphinx==8.2.3; extra == "docs"
Requires-Dist: furo==2024.8.6; extra == "docs"
Requires-Dist: myst-nb==1.2.0; extra == "docs"
Requires-Dist: myst-parser==4.0.1; extra == "docs"
Requires-Dist: sphinx-copybutton; extra == "docs"
Requires-Dist: sphinxext-opengraph; extra == "docs"
Requires-Dist: sphinx-inline-tabs; extra == "docs"
Provides-Extra: tests
Requires-Dist: pytest; extra == "tests"
Requires-Dist: coverage; extra == "tests"
Requires-Dist: pytest-cov; extra == "tests"
Provides-Extra: mypy
Requires-Dist: mypy; extra == "mypy"
Requires-Dist: numpy>=1.21; extra == "mypy"
Requires-Dist: lxml; extra == "mypy"
Requires-Dist: types-networkx; extra == "mypy"
Requires-Dist: types-psutil; extra == "mypy"
Provides-Extra: linter
Requires-Dist: ruff; extra == "linter"
Provides-Extra: dev
Requires-Dist: setuptools-scm; extra == "dev"
Dynamic: license-file
